pyhandmouse/__init__.py
pyhandmouse/main.py
pyhandmouse-1.0.3.dist-info/LICENSE
pyhandmouse-1.0.3.dist-info/METADATA
pyhandmouse-1.0.3.dist-info/WHEEL
pyhandmouse-1.0.3.dist-info/top_level.txt
pyhandmouse-1.0.3.dist-info/RECORD
