Metadata-Version: 2.1
Name: pyhandmouse
Version: 1.0.3
Summary: Hand Mouse using Python
Home-page: https://github.com/heewinkim/pyhandmouse
Author: HEESEUNG KIM
Author-email: heewin.kim@gmail.com
License: MIT
Download-URL: https://github.com/heewinkim/pyhandmouse/archive/master.zip
Platform: UNKNOWN
Classifier: Programming Language :: Python :: 3
Classifier: License :: OSI Approved :: MIT License
Classifier: Operating System :: OS Independent
Requires-Python: >=3
Requires-Dist: mediapipe (==0.8.7.2)
Requires-Dist: PyAutoGUI (==0.9.53)
Requires-Dist: opencv-python (==4.5.2.54)
Requires-Dist: utilpack
